README.md
setup.py
django_email_user.egg-info/PKG-INFO
django_email_user.egg-info/SOURCES.txt
django_email_user.egg-info/dependency_links.txt
django_email_user.egg-info/top_level.txt
email_user/__init__.py
email_user/admin.py
email_user/apps.py
email_user/forms.py
email_user/models.py