Metadata-Version: 1.0
Name: django-email-user
Version: 1.0.1
Summary: Abstract models + utils to replace `django.contrib.auth.User` with a model that uses an email address instead of a username
Home-page: https://github.com/ixc/django-email-user
Author: Interaction Consortium
Author-email: studio@interaction.net.au
License: MIT
Platform: UNKNOWN
